{
	"name": "Cropped_fiber_matrix_N_400_400",
	"local": "Ncropped",
	"header": "_data/Cropped_fiber_matrix_N_400_400.mat.json",
	"voxels": {
		"min": -1402,
		"max": 16195,
		"mean": 3860.706431,
		"std": 1968.235645,
		"size": [301,301,300]
	},
	"images": {
		"top": [
			{
				"src": "/assets/N_topslice-xy.png",
				"description": "Top XY Slice of Sample Image"
			},
			{
				"src": "/assets/N_topslice-xz.png",
				"description": "Top XZ Slice of Sample Image"
			},
			{
				"src": "/assets/N_topslice-yz.png",
				"description": "Top YZ Slice of Sample Image"
			}
		],
		"distribution": {
			"src": "/assets/Nraw-image-stats.png",
			"description": "This distribution of pixels values and their gradients."
		},
		"Peak_fit2": {
			"src": "/assets/2_peak_fit_N.png",
			"description": "This is the peak fit using 2 peaks."
		},
		"Peak_fit3": {
			"src": "/assets/3_peak_fit_N.png",
			"description": "This is the peak fit using 3 peaks."
		}
	}
}
